ropa/__init__.py
ropa/__main__.py
ropa/backend/Backend.py
ropa/backend/__init__.py
ropa/backend/constants.py
ropa/gui/__init__.py
ropa/gui/badbytes_input_controller.py
ropa/gui/export_controller.py
ropa/gui/file_dialog_controller.py
ropa/gui/filter_input_controller.py
ropa/gui/gui.py
ropa/gui/list_key_controller.py
ropa/gui/list_widget_controller.py
ropa/gui/menu_item_controller.py
ropa/ui/arch_dialog.ui
ropa/ui/scene.ui
ropa-1.0.dist-info/DESCRIPTION.rst
ropa-1.0.dist-info/METADATA
ropa-1.0.dist-info/RECORD
ropa-1.0.dist-info/WHEEL
ropa-1.0.dist-info/entry_points.txt
ropa-1.0.dist-info/metadata.json
ropa-1.0.dist-info/top_level.txt
