Metadata-Version: 2.0
Name: ropa
Version: 1.0
Summary: ropa is a Ropper-based GUI that streamlinescrafting ROP chains.
Home-page: https://orppra.github.io/ropa/
Author: Daniel Lim, Jeff Sieu, Owen Leong
Author-email: UNKNOWN
License: GNU General Public License v3.0
Platform: UNKNOWN
Requires-Dist: filebytes (>=0.9.12)
Requires-Dist: capstone (==3.0.4)
Requires-Dist: keystone-engine
Requires-Dist: ropper (==1.11.2)
Requires-Dist: pyvex
